snowday_calculator/__init__.py
snowday_calculator-0.1.1.dist-info/LICENSE
snowday_calculator-0.1.1.dist-info/METADATA
snowday_calculator-0.1.1.dist-info/WHEEL
snowday_calculator-0.1.1.dist-info/top_level.txt
snowday_calculator-0.1.1.dist-info/RECORD
